{ "height":20,
 "layers":[
        {
         "data":[21, 2, 3, 3, 3, 3, 4, 17, 22, 22, 18, 30, 19, 2, 3, 3, 3, 3, 4, 17, 22, 22, 22, 22, 19, 2, 3, 3, 3, 3, 4, 17, 22, 22, 18, 18, 19, 2, 3, 3, 3, 3, 4, 17, 22, 22, 22, 22, 19, 2, 3, 3, 3, 3, 4, 17, 2, 2, 3, 3, 19, 2, 3, 3, 3, 3, 4, 21, 12, 0, 0, 0, 0, 0, 0, 17, 18, 22, 22, 30, 19, 0, 0, 0, 0, 0, 0, 17, 22, 22, 22, 18, 19, 0, 0, 0, 0, 0, 0, 17, 18, 22, 18, 22, 19, 0, 0, 0, 0, 0, 0, 17, 22, 22, 18, 18, 19, 0, 0, 0, 0, 0, 0, 17, 2, 3, 4, 4, 19, 0, 0, 0, 0, 0, 0, 12, 20, 0, 0, 0, 0, 0, 0, 17, 22, 22, 22, 30, 19, 0, 0, 0, 0, 0, 0, 17, 29, 18, 22, 22, 19, 0, 0, 0, 0, 0, 0, 17, 18, 22, 18, 22, 19, 0, 0, 0, 0, 0, 0, 17, 18, 22, 22, 22, 19, 0, 0, 0, 0, 0, 0, 17, 4, 4, 2, 3, 19, 0, 0, 0, 0, 0, 0, 20, 20, 0, 0, 0, 0, 0, 0, 17, 18, 22, 22, 30, 19, 0, 0, 0, 0, 0, 0, 17, 18, 22, 29, 18, 19, 0, 0, 0, 0, 0, 0, 17, 22, 22, 18, 22, 19, 0, 0, 0, 0, 0, 0, 17, 18, 22, 22, 18, 19, 0, 0, 0, 0, 0, 0, 17, 2, 4, 3, 2, 19, 0, 0, 0, 0, 0, 0, 20, 20, 0, 0, 0, 0, 0, 0, 25, 26, 26, 26, 26, 27, 0, 0, 0, 0, 0, 0, 17, 18, 29, 18, 29, 19, 0, 0, 0, 0, 0, 0, 17, 22, 22, 18, 18, 19, 0, 0, 0, 0, 0, 0, 17, 18, 22, 22, 22, 19, 0, 0, 0, 0, 0, 0, 25, 26, 26, 26, 26, 27, 0, 0, 0, 0, 0, 0, 20, 20, 0, 0, 0, 0, 0, 0, 0, 0, 0, 0, 0, 0, 0, 0, 0, 0, 0, 0, 17, 18, 22, 29, 18, 19, 0, 0, 0, 0, 0, 0, 17, 22, 22, 18, 18, 19, 0, 0, 0, 0, 0, 0, 17, 36, 36, 18, 18, 19, 0, 0, 0, 0, 0, 0, 0, 0, 0, 0, 0, 0, 0, 0, 0, 0, 0, 0, 20, 20, 0, 0, 0, 0, 0, 0, 0, 0, 0, 0, 0, 0, 0, 0, 0, 0, 0, 0, 25, 26, 26, 26, 26, 27, 0, 0, 0, 0, 0, 0, 17, 18, 18, 22, 18, 19, 0, 0, 0, 0, 0, 0, 25, 26, 26, 26, 26, 27, 0, 0, 0, 0, 0, 0, 0, 0, 0, 0, 0, 0, 0, 0, 0, 0, 0, 0, 20, 20, 0, 0, 0, 0, 0, 0, 0, 0, 0, 0, 0, 0, 0, 0, 0, 0, 0, 0, 0, 0, 0, 0, 0, 0, 0, 0, 0, 0, 0, 0, 17, 21, 18, 22, 21, 19, 0, 0, 0, 0, 0, 0, 0, 0, 0, 0, 0, 0, 0, 0, 0, 0, 0, 0, 0, 0, 0, 0, 0, 0, 0, 0, 0, 0, 0, 0, 20, 20, 0, 0, 0, 0, 0, 0, 0, 0, 0, 0, 0, 0, 0, 0, 0, 0, 0, 0, 0, 0, 0, 0, 0, 0, 0, 0, 0, 0, 0, 0, 25, 26, 26, 26, 26, 27, 0, 0, 0, 0, 0, 0, 0, 0, 0, 0, 0, 0, 0, 0, 0, 0, 0, 0, 0, 0, 0, 0, 0, 0, 0, 0, 0, 0, 0, 0, 20, 20, 0, 0, 0, 0, 0, 0, 0, 0, 0, 0, 0, 0, 0, 0, 0, 0, 0, 0, 0, 0, 0, 0, 0, 0, 0, 0, 0, 0, 0, 0, 0, 0, 0, 0, 0, 0, 0, 0, 0, 0, 0, 0, 0, 0, 0, 0, 0, 0, 0, 0, 0, 0, 0, 0, 0, 0, 0, 0, 0, 0, 0, 0, 0, 0, 0, 0, 20, 2, 3, 4, 0, 0, 0, 0, 0, 0, 0, 0, 0, 0, 0, 0, 0, 0, 0, 0, 0, 0, 0, 0, 0, 0, 0, 0, 0, 0, 0, 0, 0, 0, 0, 0, 0, 0, 0, 0, 0, 0, 0, 0, 0, 0, 0, 0, 0, 0, 0, 0, 0, 0, 0, 0, 9, 10, 10, 10, 10, 11, 0, 0, 0, 0, 2, 3, 4, 20, 0, 0, 0, 0, 0, 0, 0, 0, 0, 0, 0, 0, 0, 0, 0, 0, 0, 0, 0, 0, 0, 0, 0, 0, 0, 0, 0, 0, 0, 0, 0, 0, 0, 0, 0, 0, 0, 0, 0, 0, 0, 0, 9, 10, 10, 10, 10, 11, 0, 0, 0, 0, 0, 0, 17, 3, 4, 2, 2, 19, 0, 0, 0, 0, 0, 0, 20, 20, 0, 0, 0, 0, 0, 0, 0, 0, 0, 0, 0, 0, 0, 0, 0, 0, 0, 0, 0, 0, 0, 0, 0, 0, 0, 0, 0, 0, 0, 0, 9, 10, 10, 10, 10, 11, 0, 0, 0, 0, 0, 0, 17, 22, 18, 36, 36, 19, 0, 0, 0, 0, 0, 0, 17, 2, 2, 2, 2, 19, 0, 0, 0, 0, 0, 0, 20, 20, 0, 0, 0, 0, 0, 0, 0, 0, 0, 0, 0, 0, 0, 0, 0, 0, 0, 0, 9, 10, 10, 10, 10, 11, 0, 0, 0, 0, 0, 0, 17, 21, 18, 22, 21, 19, 23, 24, 24, 23, 24, 24, 17, 22, 22, 18, 18, 19, 23, 23, 23, 23, 24, 24, 17, 4, 3, 3, 4, 19, 23, 24, 24, 23, 24, 23, 20, 20, 0, 0, 0, 0, 0, 0, 9, 10, 10, 10, 10, 11, 0, 0, 0, 0, 0, 0, 17, 29, 22, 22, 18, 19, 0, 0, 0, 0, 0, 0, 17, 22, 18, 18, 18, 19, 32, 31, 32, 31, 32, 31, 17, 22, 18, 22, 18, 19, 31, 31, 32, 32, 31, 31, 17, 3, 3, 3, 3, 19, 31, 31, 31, 32, 32, 31, 20, 20, 24, 24, 23, 23, 23, 24, 17, 18, 18, 18, 30, 19, 24, 23, 23, 24, 24, 23, 17, 18, 29, 18, 22, 19, 23, 24, 23, 24, 23, 23, 17, 22, 18, 18, 18, 19, 31, 31, 31, 32, 32, 33, 34, 35, 22, 18, 33, 34, 34, 35, 31, 31, 32, 31, 17, 3, 4, 2, 4, 19, 32, 31, 31, 32, 32, 32, 20, 20, 31, 31, 32, 31, 31, 31, 17, 22, 22, 22, 30, 19, 32, 32, 31, 32, 32, 32, 17, 18, 18, 29, 22, 19, 31, 31, 31, 31, 31, 32, 17, 22, 22, 18, 18, 19, 31, 32, 31, 31, 31, 9, 10, 11, 22, 22, 9, 10, 10, 11, 31, 31, 31, 32, 17, 3, 3, 4, 3, 19, 32, 31, 32, 32, 32, 32, 20, 20, 31, 31, 31, 32, 31, 32, 17, 22, 22, 22, 30, 19, 32, 32, 32, 32, 32, 31, 17, 18, 18, 22, 22, 19, 32, 32, 32, 32, 31, 31, 17, 22, 18, 22, 18, 19, 31, 31, 31, 32, 32, 17, 22, 19, 22, 22, 17, 22, 18, 19, 31, 32, 32, 31, 17, 3, 4, 4, 3, 19, 31, 31, 31, 32, 32, 32, 20, 20, 31, 31, 32, 32, 31, 31, 17, 18, 22, 22, 30, 19, 32, 31, 31, 31, 31, 31, 17, 22, 22, 22, 18, 19, 31, 31, 31, 31, 32, 32, 17, 22, 22, 18, 22, 19, 32, 32, 32, 31, 31, 17, 18, 19, 18, 22, 17, 18, 22, 19, 32, 31, 31, 32, 17, 4, 4, 4, 2, 19, 32, 32, 32, 31, 32, 31, 20, 20, 31, 32, 32, 31, 32, 32, 17, 18, 22, 22, 30, 19, 32, 31, 32, 32, 31, 31, 17, 18, 18, 18, 22, 19, 32, 32, 31, 32, 32, 31, 17, 22, 22, 22, 18, 19, 32, 31, 32, 32, 31, 17, 22, 19, 22, 18, 17, 22, 18, 19, 31, 32, 31, 31, 17, 3, 2, 3, 3, 19, 31, 32, 32, 31, 31, 31, 20],
         "height":20,
         "name":"Main",
         "opacity":1,
         "type":"tilelayer",
         "visible":true,
         "width":68,
         "x":0,
         "y":0
        }, 
        {
         "draworder":"topdown",
         "height":0,
         "name":"Default",
         "objects":[
                {
                 "gid":65,
                 "height":0,
                 "name":"",
                 "properties":
                    {
                     "Target":"passage"
                    },
                 "rotation":0,
                 "type":"",
                 "visible":true,
                 "width":0,
                 "x":1040,
                 "y":160
                }, 
                {
                 "gid":65,
                 "height":0,
                 "name":"",
                 "properties":
                    {
                     "Target":"hub"
                    },
                 "rotation":0,
                 "type":"",
                 "visible":true,
                 "width":0,
                 "x":16,
                 "y":160
                }, 
                {
                 "gid":81,
                 "height":0,
                 "name":"",
                 "properties":
                    {

                    },
                 "rotation":0,
                 "type":"",
                 "visible":true,
                 "width":0,
                 "x":884,
                 "y":160
                }, 
                {
                 "gid":81,
                 "height":0,
                 "name":"",
                 "properties":
                    {

                    },
                 "rotation":0,
                 "type":"",
                 "visible":true,
                 "width":0,
                 "x":700,
                 "y":176
                }, 
                {
                 "gid":81,
                 "height":0,
                 "name":"",
                 "properties":
                    {

                    },
                 "rotation":0,
                 "type":"",
                 "visible":true,
                 "width":0,
                 "x":736,
                 "y":176
                }, 
                {
                 "gid":81,
                 "height":0,
                 "name":"",
                 "properties":
                    {

                    },
                 "rotation":0,
                 "type":"",
                 "visible":true,
                 "width":0,
                 "x":552,
                 "y":192
                }, 
                {
                 "gid":81,
                 "height":0,
                 "name":"",
                 "properties":
                    {

                    },
                 "rotation":0,
                 "type":"",
                 "visible":true,
                 "width":0,
                 "x":316,
                 "y":208
                }, 
                {
                 "gid":81,
                 "height":0,
                 "name":"",
                 "properties":
                    {

                    },
                 "rotation":0,
                 "type":"",
                 "visible":true,
                 "width":0,
                 "x":356,
                 "y":208
                }, 
                {
                 "gid":81,
                 "height":0,
                 "name":"",
                 "properties":
                    {

                    },
                 "rotation":0,
                 "type":"",
                 "visible":true,
                 "width":0,
                 "x":148,
                 "y":224
                }, 
                {
                 "height":76,
                 "name":"",
                 "properties":
                    {

                    },
                 "rotation":0,
                 "type":"Lava",
                 "visible":true,
                 "width":480,
                 "x":16,
                 "y":244
                }, 
                {
                 "height":108,
                 "name":"",
                 "properties":
                    {

                    },
                 "rotation":0,
                 "type":"Lava",
                 "visible":true,
                 "width":480,
                 "x":592,
                 "y":212
                }],
         "opacity":1,
         "type":"objectgroup",
         "visible":true,
         "width":0,
         "x":0,
         "y":0
        }],
 "orientation":"orthogonal",
 "properties":
    {
     "Music":"state_of_war"
    },
 "renderorder":"right-down",
 "tileheight":16,
 "tilesets":[
        {
         "firstgid":1,
         "image":"..\/images\/tiles.png",
         "imageheight":128,
         "imagewidth":128,
         "margin":0,
         "name":"tiles",
         "properties":
            {

            },
         "spacing":0,
         "tileheight":16,
         "tilewidth":16
        }, 
        {
         "firstgid":65,
         "image":"..\/images\/props.png",
         "imageheight":128,
         "imagewidth":128,
         "margin":0,
         "name":"props",
         "properties":
            {

            },
         "spacing":0,
         "tileheight":32,
         "tilewidth":32
        }, 
        {
         "firstgid":81,
         "image":"monsters.png",
         "imageheight":64,
         "imagewidth":128,
         "margin":0,
         "name":"monsters",
         "properties":
            {

            },
         "spacing":0,
         "tileheight":32,
         "tilewidth":32
        }],
 "tilewidth":16,
 "version":1,
 "width":68
}